antgrid_server/__init__.py
antgrid_server/lora_diffusion/__init__.py
antgrid_server/lora_diffusion/cli_lora_add.py
antgrid_server/lora_diffusion/cli_lora_pti.py
antgrid_server/lora_diffusion/cli_pt_to_safetensors.py
antgrid_server/lora_diffusion/cli_svd.py
antgrid_server/lora_diffusion/dataset.py
antgrid_server/lora_diffusion/lora.py
antgrid_server/lora_diffusion/lora_manager.py
antgrid_server/lora_diffusion/preprocess_files.py
antgrid_server/lora_diffusion/safe_open.py
antgrid_server/lora_diffusion/to_ckpt_v2.py
antgrid_server/lora_diffusion/utils.py
antgrid_server/lora_diffusion/xformers_utils.py
antgrid_server/server/packageinfo.py
antgrid_server/server/register.py
antgrid_server/server/request_collections.py
antgrid_server/tritonbackend/baichuan/tritonmodel.py
antgrid_server/tritonbackend/baichuan/tritonserver.py
antgrid_server/tritonbackend/chatglm/tritonmodel.py
antgrid_server/tritonbackend/chatglm/tritonserver.py
antgrid_server/tritonbackend/llama2_7b_chat/tritonmodel.py
antgrid_server/tritonbackend/llama2_7b_chat/tritonserver.py
antgrid_server/tritonbackend/sd1_5/tritonmodel.py
antgrid_server/tritonbackend/sd1_5/tritonserver.py
antgrid_server-0.0.3.dist-info/METADATA
antgrid_server-0.0.3.dist-info/WHEEL
antgrid_server-0.0.3.dist-info/licenses/LICENSE
antgrid_server-0.0.3.dist-info/RECORD
