Metadata-Version: 2.1
Name: antgrid_server
Version: 0.0.3
Summary: A package for registering servers in Antgrid.
Project-URL: Homepage, https://github.com/pypa/sampleproject
Project-URL: Bug Tracker, https://github.com/pypa/sampleproject/issues
Author: antgrid
License-File: LICENSE
Classifier: License :: OSI Approved :: MIT License
Classifier: Operating System :: OS Independent
Classifier: Programming Language :: Python :: 3
Requires-Python: ==3.8.*
Requires-Dist: accelerate
Requires-Dist: colorama
Requires-Dist: cpm-kernels
Requires-Dist: diffusers==0.14
Requires-Dist: fire
Requires-Dist: ftfy
Requires-Dist: mediapipe
Requires-Dist: numpy
Requires-Dist: nvidia-pytriton
Requires-Dist: opencv-python
Requires-Dist: pillow
Requires-Dist: safetensors
Requires-Dist: scipy
Requires-Dist: sentencepiece
Requires-Dist: streamlit
Requires-Dist: torch
Requires-Dist: torchvision
Requires-Dist: transformers
Requires-Dist: transformers-stream-generator
Requires-Dist: wandb
Requires-Dist: websocket-client
